pygrestqlambda/__init__.py
pygrestqlambda/controller.py
pygrestqlambda/aws/__init__.py
pygrestqlambda/aws/lambda_function/__init__.py
pygrestqlambda/aws/lambda_function/json_transform.py
pygrestqlambda/aws/lambda_function/rest_api_gateway_proxy_integration/__init__.py
pygrestqlambda/aws/lambda_function/rest_api_gateway_proxy_integration/request.py
pygrestqlambda/aws/lambda_function/rest_api_gateway_proxy_integration/response.py
pygrestqlambda/db/__init__.py
pygrestqlambda/db/record.py
pygrestqlambda-0.0.9.dist-info/METADATA
pygrestqlambda-0.0.9.dist-info/WHEEL
pygrestqlambda-0.0.9.dist-info/licenses/LICENSE
pygrestqlambda-0.0.9.dist-info/RECORD
