Metadata-Version: 2.4
Name: pygrestqlambda
Version: 0.0.9
Summary: PostgreSQL REST API framework for AWS Lambda functions
Project-URL: Homepage, https://github.com/mesogate/pygrestqlambda
Project-URL: Issues, https://github.com/mesogate/pygrestqlambda/issues
Author-email: Voquis Limited <opensource@voquis.com>
License-File: LICENSE
Classifier: License :: OSI Approved :: MIT License
Classifier: Operating System :: OS Independent
Classifier: Programming Language :: Python :: 3
Requires-Python: >=3.11
Requires-Dist: aws-xray-sdk
Requires-Dist: boto3
Provides-Extra: dev
Requires-Dist: build; extra == 'dev'
Requires-Dist: docker; extra == 'dev'
Requires-Dist: httpx; extra == 'dev'
Requires-Dist: psycopg[binary]; extra == 'dev'
Requires-Dist: pylint; extra == 'dev'
Requires-Dist: pyright; extra == 'dev'
Requires-Dist: pytest; extra == 'dev'
Requires-Dist: pytest-cov; extra == 'dev'
Requires-Dist: pytest-xdist; extra == 'dev'
Requires-Dist: ruff; extra == 'dev'
Requires-Dist: twine; extra == 'dev'
